auth0_api_python/__init__.py
auth0_api_python/api_client.py
auth0_api_python/config.py
auth0_api_python/errors.py
auth0_api_python/token_utils.py
auth0_api_python/utils.py
auth0_api_python-1.0.0b5.dist-info/LICENSE
auth0_api_python-1.0.0b5.dist-info/METADATA
auth0_api_python-1.0.0b5.dist-info/WHEEL
auth0_api_python-1.0.0b5.dist-info/RECORD
