Metadata-Version: 2.3
Name: auth0-api-python
Version: 1.0.0b5
Summary: SDK for verifying access tokens and securing APIs with Auth0, using Authlib.
License: MIT
Author: Auth0
Author-email: support@auth0.com
Requires-Python: >=3.9,<4.0
Classifier: License :: OSI Approved :: MIT License
Classifier: Programming Language :: Python :: 3
Classifier: Programming Language :: Python :: 3.9
Classifier: Programming Language :: Python :: 3.10
Classifier: Programming Language :: Python :: 3.11
Classifier: Programming Language :: Python :: 3.12
Classifier: Programming Language :: Python :: 3.13
Requires-Dist: ada-url (>=1.25.0,<2.0.0)
Requires-Dist: authlib (>=1.0,<2.0)
Requires-Dist: httpx (>=0.28.1,<0.29.0)
Requires-Dist: requests (>=2.31.0,<3.0.0)
